uvicorn_context_manager/__init__.py
uvicorn_context_manager/context_manager.py
uvicorn_context_manager-0.0.1.dist-info/METADATA
uvicorn_context_manager-0.0.1.dist-info/WHEEL
uvicorn_context_manager-0.0.1.dist-info/licenses/LICENSE
uvicorn_context_manager-0.0.1.dist-info/RECORD
