Metadata-Version: 2.1
Name: uvicorn_context_manager
Version: 0.0.1
Summary: 🚀 Context Manager to run `uvicorn` ASGI applications
Project-URL: Documentation, https://alvarobartt.github.io/uvicorn_context_manager
Project-URL: Issues, https://github.com/alvarobartt/uvicorn_context_manager/issues
Project-URL: Source, https://github.com/alvarobartt/uvicorn_context_manager
Author-email: Alvaro Bartolome <alvarobartt@gmail.com>
License-Expression: MIT
License-File: LICENSE
Classifier: Development Status :: 4 - Beta
Classifier: Programming Language :: Python
Classifier: Programming Language :: Python :: 3.7
Classifier: Programming Language :: Python :: 3.8
Classifier: Programming Language :: Python :: 3.9
Classifier: Programming Language :: Python :: 3.10
Classifier: Programming Language :: Python :: Implementation :: CPython
Classifier: Programming Language :: Python :: Implementation :: PyPy
Requires-Python: >=3.7
Requires-Dist: uvicorn~=0.20.0
Provides-Extra: docs
Requires-Dist: mkdocs-git-revision-date-localized-plugin~=1.1.0; extra == 'docs'
Requires-Dist: mkdocs-material~=8.5.4; extra == 'docs'
Requires-Dist: mkdocstrings[python]~=0.19.0; extra == 'docs'
Requires-Dist: mkdocs~=1.4.0; extra == 'docs'
Provides-Extra: quality
Requires-Dist: black~=22.10.0; extra == 'quality'
Requires-Dist: pre-commit~=2.20.0; extra == 'quality'
Requires-Dist: ruff~=0.0.245; extra == 'quality'
Provides-Extra: tests
Requires-Dist: fastapi~=0.91.0; extra == 'tests'
Requires-Dist: httpx~=0.23.3; extra == 'tests'
Requires-Dist: pytest~=7.1.2; extra == 'tests'
